{"poi": [{"lat": 0.8033409231549422, "lon": 112.08045238730539, "label": "Water", "description": "Water description", "color": "#0000ff"}, {"lat": 0.8052290122628606, "lon": 112.0730709480964, "label": "Water", "description": "Water description", "color": "#0000ff"}, {"lat": 0.8112365626876176, "lon": 112.06671947714914, "label": "Water", "description": "Water description", "color": "#0000ff"}, {"lat": 0.8103783417429103, "lon": 112.0639728951179, "label": "Water", "description": "Water description", "color": "#0000ff"}, {"lat": 0.8079753221309505, "lon": 112.06311458823312, "label": "Water", "description": "Water description", "color": "#0000ff"}, {"lat": 0.8179306797943621, "lon": 112.07547420737374, "label": "Water", "description": "Water description", "color": "#0000ff"}, {"lat": 0.8232516367135165, "lon": 112.07049602744212, "label": "Water", "description": "Water description", "color": "#0000ff"}, {"lat": 0.8232516367135165, "lon": 112.06465954062571, "label": "Water", "description": "Water description", "color": "#0000ff"}, {"lat": 0.8187888991306626, "lon": 112.07049602744212, "label": "Water", "description": "Water description", "color": "#0000ff"}, {"lat": 0.8033409231549422, "lon": 112.0895504402839, "label": "Water", "description": "Water description", "color": "#0000ff"}, {"lat": 0.744592171764476, "lon": 112.10814468849642, "label": "Water", "description": "Water description", "color": "#0000ff"}, {"lat": 0.7437339372728575, "lon": 112.10591309059602, "label": "Water", "description": "Water description", "color": "#0000ff"}, {"lat": 0.7413308798091418, "lon": 112.10591309059602, "label": "Water", "description": "Water description", "color": "#0000ff"}, {"lat": 0.7751452093737808, "lon": 112.03433029640658, "label": "Water", "description": "Water description", "color": "#0000ff"}, {"lat": 0.7751452093737808, "lon": 112.03540318001252, "label": "Water", "description": "Water description", "color": "#0000ff"}, {"lat": 0.7744157152234223, "lon": 112.03484528053744, "label": "Water", "description": "Water description", "color": "#0000ff"}, {"lat": 0.7730854608614577, "lon": 112.03445904243928, "label": "Water", "description": "Water description", "color": "#0000ff"}, {"lat": 0.7716693831795003, "lon": 112.0343732117508, "label": "Water", "description": "Water description", "color": "#0000ff"}, {"lat": 0.7700816591573807, "lon": 112.03424446571809, "label": "Water", "description": "Water description", "color": "#0000ff"}, {"lat": 0.7685797575110622, "lon": 112.03355782021028, "label": "Water", "description": "Water description", "color": "#0000ff"}, {"lat": 0.7659621562371438, "lon": 112.03325741280061, "label": "Water", "description": "Water description", "color": "#0000ff"}, {"lat": 0.7531277766083541, "lon": 112.03678236899991, "label": "Water", "description": "Water description", "color": "#0000ff"}, {"lat": 0.7526986602187756, "lon": 112.03703986106534, "label": "Water", "description": "Water description", "color": "#0000ff"}, {"lat": 0.7509821942384151, "lon": 112.03806982932706, "label": "Water", "description": "Water description", "color": "#0000ff"}, {"lat": 0.7501239609953805, "lon": 112.03871355949062, "label": "Water", "description": "Water description", "color": "#0000ff"}, {"lat": 0.7489224341724218, "lon": 112.03905688224454, "label": "Water", "description": "Water description", "color": "#0000ff"}, {"lat": 0.746691026342027, "lon": 112.04030142722743, "label": "Water", "description": "Water description", "color": "#0000ff"}, {"lat": 0.7453178517293877, "lon": 112.04094515739101, "label": "Water", "description": "Water description", "color": "#0000ff"}, {"lat": 0.7437301180498703, "lon": 112.04201804099698, "label": "Water", "description": "Water description", "color": "#0000ff"}, {"lat": 0.7437301180498702, "lon": 112.0430480092587, "label": "Water", "description": "Water description", "color": "#0000ff"}, {"lat": 0.7475063485653867, "lon": 112.04467879233975, "label": "Water", "description": "Water description", "color": "#0000ff"}, {"lat": 0.7245813282513627, "lon": 112.02232793781698, "label": "Land", "description": "Land description", "color": "#ffff99"}, {"lat": 0.7203759588718447, "lon": 112.02112630817831, "label": "Land", "description": "Land description", "color": "#ffff99"}, {"lat": 0.7183161846971525, "lon": 112.02258542988241, "label": "Land", "description": "Land description", "color": "#ffff99"}, {"lat": 0.7165997055089407, "lon": 112.02258542988241, "label": "Land", "description": "Land description", "color": "#ffff99"}, {"lat": 0.7138533374706174, "lon": 112.02945188496052, "label": "Land", "description": "Land description", "color": "#ffff99"}, {"lat": 0.7293874599037656, "lon": 112.0049901387447, "label": "Land", "description": "Land description", "color": "#ffff99"}, {"lat": 0.7577812327295144, "lon": 111.9854144662882, "label": "Land", "description": "Land description", "color": "#ffff99"}, {"lat": 0.7574379399887858, "lon": 111.98455615940344, "label": "Land", "description": "Land description", "color": "#ffff99"}, {"lat": 0.713839545097935, "lon": 112.02112003269445, "label": "Land", "description": "Land description", "color": "#ffff99"}, {"lat": 0.7670501264053112, "lon": 112.04266353550206, "label": "Land", "description": "Land description", "color": "#ffff99"}, {"lat": 0.7119470301542747, "lon": 112.02716368997763, "label": "Land", "description": "Land description", "color": "#ffff99"}, {"lat": 0.7108098611874551, "lon": 112.01907414758871, "label": "Land", "description": "Land description", "color": "#ffff99"}, {"lat": 0.712268870377012, "lon": 112.01909560526083, "label": "Land", "description": "Land description", "color": "#ffff99"}, {"lat": 0.7153799913698142, "lon": 112.01722878778648, "label": "Land", "description": "Land description", "color": "#ffff99"}, {"lat": 0.7119899421852893, "lon": 112.01420325601768, "label": "Land", "description": "Land description", "color": "#ffff99"}, {"lat": 0.7107884051665281, "lon": 112.01409596765707, "label": "Land", "description": "Land description", "color": "#ffff99"}, {"lat": 0.709715603992753, "lon": 112.0138813909359, "label": "Land", "description": "Land description", "color": "#ffff99"}, {"lat": 0.708878818904447, "lon": 112.01422471368979, "label": "Land", "description": "Land description", "color": "#ffff99"}, {"lat": 0.7302687389217013, "lon": 112.00544557057859, "label": "Land", "description": "Land description", "color": "#ffff99"}, {"lat": 0.7293675898032649, "lon": 112.00559577428342, "label": "Land", "description": "Land description", "color": "#ffff99"}, {"lat": 0.7287668236240604, "lon": 112.00583180867673, "label": "Land", "description": "Land description", "color": "#ffff99"}, {"lat": 0.7634834353283559, "lon": 111.99829407586354, "label": "Land", "description": "Land description", "color": "#ffff99"}, {"lat": 0.7623677352946503, "lon": 111.99829407586354, "label": "Land", "description": "Land description", "color": "#ffff99"}, {"lat": 0.7618527967200152, "lon": 111.99837990655202, "label": "Land", "description": "Land description", "color": "#ffff99"}, {"lat": 0.8191172302565305, "lon": 111.99683495415943, "label": "Land", "description": "Land description", "color": "#ffff99"}, {"lat": 0.8191172302565305, "lon": 111.99816532983081, "label": "Land", "description": "Land description", "color": "#ffff99"}, {"lat": 0.8183448329253687, "lon": 111.99876614465015, "label": "Land", "description": "Land description", "color": "#ffff99"}, {"lat": 0.8138820898819353, "lon": 111.9949037636687, "label": "Land", "description": "Land description", "color": "#ffff99"}, {"lat": 0.813753356836117, "lon": 111.99374504937428, "label": "Land", "description": "Land description", "color": "#ffff99"}, {"lat": 0.8126376702670606, "lon": 111.99391671075124, "label": "Land", "description": "Land description", "color": "#ffff99"}, {"lat": 0.7769474883242535, "lon": 112.08471291054232, "label": "Forest", "description": "Forest description", "color": "#00b200"}, {"lat": 0.7695667213335727, "lon": 112.089519429097, "label": "Forest", "description": "Forest description", "color": "#00b200"}, {"lat": 0.7613277105435964, "lon": 112.0891761063431, "label": "Forest", "description": "Forest description", "color": "#00b200"}, {"lat": 0.7494841049945624, "lon": 112.1386145829056, "label": "Forest", "description": "Forest description", "color": "#00b200"}, {"lat": 0.7503423383631016, "lon": 112.14410774696809, "label": "Forest", "description": "Forest description", "color": "#00b200"}, {"lat": 0.752402097760313, "lon": 112.07098000038606, "label": "Forest", "description": "Forest description", "color": "#00b200"}, {"lat": 0.7450212887715781, "lon": 112.07132332313998, "label": "Forest", "description": "Forest description", "color": "#00b200"}, {"lat": 0.7487975181786335, "lon": 112.01879494179231, "label": "Forest", "description": "Forest description", "color": "#00b200"}, {"lat": 0.7487975181786335, "lon": 112.01622002113803, "label": "Forest", "description": "Forest description", "color": "#00b200"}, {"lat": 0.7548051491611281, "lon": 112.09037773598178, "label": "Forest", "description": "Forest description", "color": "#00b200"}, {"lat": 0.7634732879692105, "lon": 112.07166664589387, "label": "Forest", "description": "Forest description", "color": "#00b200"}, {"lat": 0.7626150571976962, "lon": 112.07329742897494, "label": "Forest", "description": "Forest description", "color": "#00b200"}, {"lat": 0.7608556835813766, "lon": 112.07321159828645, "label": "Forest", "description": "Forest description", "color": "#00b200"}, {"lat": 0.741142591347979, "lon": 112.01653646333669, "label": "Forest", "description": "Forest description", "color": "#00b200"}, {"lat": 0.7382245911225299, "lon": 112.01636480195974, "label": "Forest", "description": "Forest description", "color": "#00b200"}, {"lat": 0.7452621178034807, "lon": 112.01190160615897, "label": "Forest", "description": "Forest description", "color": "#00b200"}, {"lat": 0.7457770583399586, "lon": 112.01893972261405, "label": "Forest", "description": "Forest description", "color": "#00b200"}, {"lat": 0.7438889427453476, "lon": 112.01893972261405, "label": "Forest", "description": "Forest description", "color": "#00b200"}, {"lat": 0.7519563400668053, "lon": 112.06837819917655, "label": "Forest", "description": "Forest description", "color": "#00b200"}, {"lat": 0.7996738267434282, "lon": 111.93027662141776, "label": "Forest", "description": "Forest description", "color": "#00b200"}, {"lat": 0.8011328060747139, "lon": 111.92778753145194, "label": "Forest", "description": "Forest description", "color": "#00b200"}, {"lat": 0.8011328060747139, "lon": 111.92478345735525, "label": "Forest", "description": "Forest description", "color": "#00b200"}, {"lat": 0.7989014257109789, "lon": 111.92478345735525, "label": "Forest", "description": "Forest description", "color": "#00b200"}, {"lat": 0.7971849784525844, "lon": 111.92547010286306, "label": "Forest", "description": "Forest description", "color": "#00b200"}, {"lat": 0.7992447150766554, "lon": 111.92675756319021, "label": "Forest", "description": "Forest description", "color": "#00b200"}, {"lat": 0.7958976425391667, "lon": 111.92813085420585, "label": "Forest", "description": "Forest description", "color": "#00b200"}, {"lat": 0.7948677735190887, "lon": 111.92692922456717, "label": "Forest", "description": "Forest description", "color": "#00b200"}, {"lat": 0.8160658586042092, "lon": 111.93336652620292, "label": "Forest", "description": "Forest description", "color": "#00b200"}, {"lat": 0.7837052863746586, "lon": 111.97524634529135, "label": "Forest", "description": "Forest description", "color": "#00b200"}, {"lat": 0.7845635128806168, "lon": 111.97320786644003, "label": "Forest", "description": "Forest description", "color": "#00b200"}, {"lat": 0.7830401607115961, "lon": 111.97380868125937, "label": "Forest", "description": "Forest description", "color": "#00b200"}], "polygonUrl": "https://raw.githubusercontent.com/dngghuy/sample_kml/main/sample_geometry_753v4.kml"}